{
  "project_info": {
    "project_number": "540466446708",
    "project_id": "freebitedemo2024",
    "storage_bucket": "freebitedemo2024.appspot.com"
  },
  "client": [
    {
      "client_info": {
        "mobilesdk_app_id": "1:540466446708:android:a80f2f25b88d140028ac21",
        "android_client_info": {
          "package_name": "com.example.freebite2"
        }
      },
      "oauth_client": [],
      "api_key": [
        {
          "current_key": "AIzaSyB3nE9qxxqj7UUHwXB2Y_OU3virBr4aFZ0"
        }
      ],
      "services": {
        "appinvite_service": {
          "other_platform_oauth_client": []
        }
      }
    }
  ],
  "configuration_version": "1"
}